physics_plot/__init__.py
physics_plot/colors/colorblind.mplstyle
physics_plot/colors/ggplot.mplstyle
physics_plot/pp_base.mplstyle
physics_plot/py.typed
physics_plot/utils.py
physics_plot-0.2.3.dist-info/WHEEL
physics_plot-0.2.3.dist-info/METADATA
physics_plot-0.2.3.dist-info/RECORD
