Metadata-Version: 2.3
Name: physics-plot
Version: 0.2.3
Summary: Publication-quality Matplotlib styling and helper utilities for scientific plots
Author: Cory Chu
Author-email: Cory Chu <cory@gwlab.page>
Requires-Python: >=3.9
Project-URL: Documentation, https://c0rychu.github.io/physics-plot/
Project-URL: Homepage, https://github.com/c0rychu/physics-plot
Project-URL: Issues, https://github.com/c0rychu/physics-plot/issues
Project-URL: Repository, https://github.com/c0rychu/physics-plot.git
